MANIFEST.in
README.md
RunSnakeRun.desktop
license.txt
pyproject.toml
setup.py
RunSnakeRun.egg-info/PKG-INFO
RunSnakeRun.egg-info/SOURCES.txt
RunSnakeRun.egg-info/dependency_links.txt
RunSnakeRun.egg-info/entry_points.txt
RunSnakeRun.egg-info/not-zip-safe
RunSnakeRun.egg-info/requires.txt
RunSnakeRun.egg-info/top_level.txt
runsnakerun/__init__.py
runsnakerun/_meliaejson.py
runsnakerun/austinloader.py
runsnakerun/coldshotadapter.py
runsnakerun/homedirectory.py
runsnakerun/listviews.py
runsnakerun/macshim.py
runsnakerun/meliaeadapter.py
runsnakerun/meliaeloader.py
runsnakerun/pstatsadapter.py
runsnakerun/pstatsloader.py
runsnakerun/runsnake.py
runsnakerun/speedscopeadapter.py
runsnakerun/speedscopeloader.py
tests/test_meliaeloader.py
tests/test_speedscopeloader.py