Metadata-Version: 2.1
Name: RunSnakeRun
Version: 3.0.0
Summary: GUI Viewer for Python profiling runs
Home-page: https://github.com/mcfletch/runsnakerun
Download-URL: https://pypi.org/project/RunSnakeRun/
Author: Mike C. Fletcher
Author-email: mcfletch@vrplumber.com
License: BSD
Keywords: profile,gui,wxPython,squaremap
Platform: Any
Classifier: License :: OSI Approved :: BSD License
Classifier: Programming Language :: Python :: 2
Classifier: Programming Language :: Python :: 3
Classifier: Topic :: Software Development :: Libraries :: Python Modules
Classifier: Intended Audience :: Developers
Requires-Dist: pathlib2
Requires-Dist: six
Requires-Dist: SquareMap>=1.0.5
Requires-Dist: wxPython
